MANIFEST.in
README.md
README.rst
setup.cfg
setup.py
nr_common/__init__.py
nr_common/configreader.py
nr_common/mproc.py
nr_common/pickler.py
nr_common.egg-info/PKG-INFO
nr_common.egg-info/SOURCES.txt
nr_common.egg-info/dependency_links.txt
nr_common.egg-info/not-zip-safe
nr_common.egg-info/requires.txt
nr_common.egg-info/top_level.txt
nr_common/blueprints/__init__.py
nr_common/blueprints/job_status/__init__.py
nr_common/blueprints/job_status/db_api.py
nr_common/blueprints/job_status/job_status.py
nr_common/blueprints/job_status/models.py
nr_common/blueprints/job_status/utils.py
nr_common/blueprints/job_status/web_api.py
nr_common/fs_utils/__init__.py
nr_common/fs_utils/fs_utils.py
nr_common/image_utils/__init__.py
nr_common/image_utils/image_utils.py
nr_common/image_utils/image_utils_caffe.py
nr_common/image_utils/image_utils_cv2.py
nr_common/image_utils/image_utils_meta.py
nr_common/image_utils/image_utils_pil.py