Metadata-Version: 1.1
Name: nr-common
Version: 0.1.6
Summary: Common python functionalities aimed to be at least compatible with Python3.
Home-page: https://github.com/nitred/nr-common
Author: Nitish Reddy Koripalli
Author-email: UNKNOWN
License: UNKNOWN
Download-URL: https://github.com/nitred/nr-common/archive/0.1.6.tar.gz
Platform: UNKNOWN
Classifier: Programming Language :: Python :: 3.5
Classifier: Programming Language :: Python :: 3.6
